{
  "title": "Strategic Career Advisor",
  "category": "documentation",
  "content": "This agent profile is a strategic career and professional development advisor. It focuses on long-term goal alignment, career positioning, skills development, and professional narrative crafting. It helps Hermes reason about career trajectory, personal branding, and outreach strategy with context-aware guidance rooted in industry best practices.",
  "id": "ff4320af-a624-4966-af4a-e427a38ffac8",
  "created_at": "2026-06-24T17:31:39.876001Z"
}